.gitignore
MANIFEST.in
README.rst
bise.diazotheme-configure.zcml
bootstrap.py
buildout.cfg
setup.py
bise/__init__.py
bise.diazotheme.egg-info/PKG-INFO
bise.diazotheme.egg-info/SOURCES.txt
bise.diazotheme.egg-info/dependency_links.txt
bise.diazotheme.egg-info/entry_points.txt
bise.diazotheme.egg-info/namespace_packages.txt
bise.diazotheme.egg-info/not-zip-safe
bise.diazotheme.egg-info/requires.txt
bise.diazotheme.egg-info/top_level.txt
bise/diazotheme/__init__.py
bise/diazotheme/configure.zcml
bise/diazotheme/events.py
bise/diazotheme/interfaces.py
bise/diazotheme/tests.py
bise/diazotheme/upgrades.py
bise/diazotheme/upgrades.zcml
bise/diazotheme/version.txt
bise/diazotheme/browser/__init__.py
bise/diazotheme/browser/admin.py
bise/diazotheme/browser/configure.zcml
bise/diazotheme/browser/frontpage.py
bise/diazotheme/browser/pt/.frontpage-news.pt.un~
bise/diazotheme/browser/pt/frontpage-news.pt
bise/diazotheme/browser/pt/frontpage-news.pt~
bise/diazotheme/browser/pt/simplified-listing.pt
bise/diazotheme/profiles/default/browserlayer.xml
bise/diazotheme/profiles/default/cssregistry.xml
bise/diazotheme/profiles/default/jsregistry.xml
bise/diazotheme/profiles/default/metadata.xml
bise/diazotheme/profiles/default/registry.xml
bise/diazotheme/profiles/default/skins.xml
bise/diazotheme/profiles/default/theme.xml
bise/diazotheme/profiles/default/viewlets.xml
bise/diazotheme/skins/bise_diazotheme_custom/main_template.pt
bise/diazotheme/static/.homepage.html.un~
bise/diazotheme/static/catalogue.html
bise/diazotheme/static/edit.html
bise/diazotheme/static/folder.html
bise/diazotheme/static/homepage.html
bise/diazotheme/static/homepage.html~
bise/diazotheme/static/index.html
bise/diazotheme/static/manifest.cfg
bise/diazotheme/static/package.json
bise/diazotheme/static/page.html
bise/diazotheme/static/rules.xml
bise/diazotheme/static/scrap.xml
bise/diazotheme/static/css/admin.css
bise/diazotheme/static/css/fixes.css
bise/diazotheme/static/css/main.css
bise/diazotheme/static/img/bg-card-calendar.png
bise/diazotheme/static/img/bg-interactive-presentation-card.jpg
bise/diazotheme/static/img/bg-pattern-greendustscratch.png
bise/diazotheme/static/img/bg-pattern-paperfibers.png
bise/diazotheme/static/img/bg-pattern-randomgreenvariations.png
