Metadata-Version: 1.1
Name: bise.diazotheme
Version: 1.4.dev0
Summary: Bise Theme for Diazo
Home-page: https://github.com/eea/bise.diazotheme
Author: Tiberiu Ichim
Author-email: tiberiu.ichim@eaudeweb.ro
License: GPL
Platform: UNKNOWN
Classifier: Programming Language :: Python
Classifier: Framework :: Plone
Classifier: Framework :: Plone :: 4.0
Classifier: Framework :: Plone :: 4.1
Classifier: Framework :: Plone :: 4.2
